senda/Model.py
senda/__init__.py
senda/angry_tweets.py
senda-0.7.7.dist-info/LICENSE
senda-0.7.7.dist-info/METADATA
senda-0.7.7.dist-info/WHEEL
senda-0.7.7.dist-info/top_level.txt
senda-0.7.7.dist-info/RECORD
