Metadata-Version: 2.1
Name: senda
Version: 0.7.7
Summary: Framework for Fine-tuning Transformers for Sentiment Analysis
Home-page: https://github.com/ebanalyse/senda
Author: Lars Kjeldgaard
Author-email: lars.kjeldgaard@eb.dk
License: UNKNOWN
Platform: UNKNOWN
Classifier: Programming Language :: Python :: 3
Classifier: License :: OSI Approved :: MIT License
Requires-Python: >=3.7
Requires-Dist: torch
Requires-Dist: transformers
Requires-Dist: sklearn
Requires-Dist: nltk
Requires-Dist: pandas
Requires-Dist: pyconll
Requires-Dist: tweepy
Requires-Dist: danlp
Requires-Dist: datasets
Requires-Dist: numpy
